Metadata-Version: 2.1
Name: fast-json-server
Version: 0.0.1
Summary: fast-json-server provides a full REST API / GraphQL Server with zero coding in few seconds.
Home-page: https://github.com/scionoftech/fast-json-server
Author: Sai Kumar Yava
License: MIT
Keywords: fastapi,json,json server,fake server,graphql
Platform: UNKNOWN
Classifier: Development Status :: 5 - Production/Stable
Classifier: Programming Language :: Python
Classifier: Programming Language :: Python :: 3.6
Classifier: Programming Language :: Python :: 3.7
Classifier: Programming Language :: Python :: 3.8
Classifier: License :: OSI Approved :: MIT License
